{
	"format_version": "1.12.0",
	"minecraft:geometry": [
		{
			"description": {
				"identifier": "geometry.pixelmind.nine_tailed_fox",
				"texture_width": 512,
				"texture_height": 512,
				"visible_bounds_width": 15,
				"visible_bounds_height": 8,
				"visible_bounds_offset": [0, 2, 0]
			},
			"bones": [
				{
					"name": "hip",
					"pivot": [0, -4, 35.5],
					"cubes": [
						{"origin": [-7, -11, 31], "size": [14, 14, 9], "uv": [96, 116]}
					]
				},
				{
					"name": "LeftLeg",
					"parent": "hip",
					"pivot": [6.5, -7.25, 34.5],
					"cubes": [
						{"origin": [3, -20.5, 29], "size": [7, 17.5, 10], "uv": [155, 28]}
					]
				},
				{
					"name": "LeftLeg2",
					"parent": "LeftLeg",
					"pivot": [6.5, -20, 31],
					"cubes": [
						{"origin": [4, -21.5, 30], "size": [5, 5.5, 14], "uv": [117, 178]}
					]
				},
				{
					"name": "LeftLeg3",
					"parent": "LeftLeg2",
					"pivot": [6.5, -18.25, 43],
					"cubes": [
						{"origin": [5, -29.5, 41], "size": [3, 12.5, 4], "uv": [0, 29]}
					]
				},
				{
					"name": "LeftLeg4",
					"parent": "LeftLeg3",
					"pivot": [6.625, -28.125, 42.875],
					"cubes": [
						{"origin": [4.5, -30.5, 38], "size": [4.25, 2.5, 7.25], "uv": [60, 143]},
						{"origin": [6, -29.75, 37.25], "size": [1.25, 2, 2.75], "uv": [39, 40]},
						{"origin": [4.25, -29.75, 37.75], "size": [1.25, 2, 1.75], "uv": [5, 72]},
						{"origin": [7.75, -29.75, 37.75], "size": [1.25, 2, 1.75], "uv": [0, 72]}
					]
				},
				{
					"name": "RightLeg",
					"parent": "hip",
					"pivot": [-6.5, -7.25, 34.5],
					"cubes": [
						{"origin": [-10, -20.5, 29], "size": [7, 17.5, 10], "uv": [152, 0]}
					]
				},
				{
					"name": "RightLeg2",
					"parent": "RightLeg",
					"pivot": [-6.5, -20, 31],
					"cubes": [
						{"origin": [-9, -21.5, 30], "size": [5, 5.5, 14], "uv": [171, 177]}
					]
				},
				{
					"name": "RightLeg3",
					"parent": "RightLeg2",
					"pivot": [-6.5, -18.25, 43],
					"cubes": [
						{"origin": [-8, -29.5, 41], "size": [3, 12.5, 4], "uv": [0, 0]}
					]
				},
				{
					"name": "RightLeg4",
					"parent": "RightLeg3",
					"pivot": [-6.625, -28.125, 42.875],
					"cubes": [
						{"origin": [-8.75, -30.5, 38], "size": [4.25, 2.5, 7.25], "uv": [72, 0]},
						{"origin": [-7.25, -29.75, 37.25], "size": [1.25, 2, 2.75], "uv": [39, 0]},
						{"origin": [-5.5, -29.75, 37.75], "size": [1.25, 2, 1.75], "uv": [71, 0]},
						{"origin": [-9, -29.75, 37.75], "size": [1.25, 2, 1.75], "uv": [0, 58]}
					]
				},
				{
					"name": "tail",
					"parent": "hip",
					"pivot": [0, -2.625, 40],
					"cubes": [
						{"origin": [-2.375, -5, 36], "size": [4.75, 4.75, 12], "uv": [83, 215]}
					]
				},
				{
					"name": "tail2",
					"parent": "tail",
					"pivot": [0, -2.625, 46.25],
					"cubes": [
						{"origin": [-3.375, -6, 46], "size": [6.75, 6.75, 10], "uv": [212, 181]}
					]
				},
				{
					"name": "tail3",
					"parent": "tail2",
					"pivot": [0, -2.625, 55],
					"cubes": [
						{"origin": [-4.375, -7, 55], "size": [8.75, 8.75, 13], "uv": [0, 140]}
					]
				},
				{
					"name": "tail4",
					"parent": "tail3",
					"pivot": [0, -2.625, 65.5],
					"cubes": [
						{"origin": [-5.375, -8, 83], "size": [10.75, 10.75, 7], "uv": [194, 105]},
						{"origin": [-5.375, -8, 65], "size": [10.75, 10.75, 18], "uv": [39, 69]}
					]
				},
				{
					"name": "tail5",
					"parent": "tail4",
					"pivot": [0, -2.625, 82.5],
					"cubes": [
						{"origin": [-4.375, -7, 80], "size": [8.75, 8.75, 12], "uv": [165, 113]},
						{"origin": [-4.375, -7, 92], "size": [8.75, 8.75, 5], "uv": [223, 237]}
					]
				},
				{
					"name": "tail6",
					"parent": "tail5",
					"pivot": [0, -2.625, 92.5],
					"cubes": [
						{"origin": [-3.375, -6, 90], "size": [6.75, 6.75, 8], "uv": [229, 105]}
					]
				},
				{
					"name": "tail7",
					"parent": "tail6",
					"pivot": [0, -2.625, 99],
					"cubes": [
						{"origin": [-2.375, -5, 98], "size": [4.75, 4.75, 6], "uv": [252, 155]},
						{"origin": [-2.375, -5, 104], "size": [4.75, 4.75, 4], "uv": [155, 77]}
					]
				},
				{
					"name": "1_tail",
					"parent": "hip",
					"pivot": [0, 0.52227, 39.00767],
					"rotation": [17.5, 0, 0],
					"cubes": [
						{"origin": [-2.375, -1.85273, 35.00767], "size": [4.75, 4.75, 12], "uv": [83, 215]}
					]
				},
				{
					"name": "1_tail2",
					"parent": "1_tail",
					"pivot": [0, 0.52227, 45.25767],
					"cubes": [
						{"origin": [-3.375, -2.85273, 45.00767], "size": [6.75, 6.75, 10], "uv": [212, 181]}
					]
				},
				{
					"name": "1_tail3",
					"parent": "1_tail2",
					"pivot": [0, 0.52227, 54.00767],
					"cubes": [
						{"origin": [-4.375, -3.85273, 54.00767], "size": [8.75, 8.75, 13], "uv": [0, 140]}
					]
				},
				{
					"name": "1_tail4",
					"parent": "1_tail3",
					"pivot": [0, 0.52227, 64.50767],
					"cubes": [
						{"origin": [-5.375, -4.85273, 82.00767], "size": [10.75, 10.75, 7], "uv": [194, 105]},
						{"origin": [-5.375, -4.85273, 64.00767], "size": [10.75, 10.75, 18], "uv": [39, 69]}
					]
				},
				{
					"name": "1_tail5",
					"parent": "1_tail4",
					"pivot": [0, 0.52227, 81.50767],
					"cubes": [
						{"origin": [-4.375, -3.85273, 79.00767], "size": [8.75, 8.75, 12], "uv": [165, 113]},
						{"origin": [-4.375, -3.85273, 91.00767], "size": [8.75, 8.75, 5], "uv": [223, 237]}
					]
				},
				{
					"name": "1_tail6",
					"parent": "1_tail5",
					"pivot": [0, 0.52227, 91.50767],
					"cubes": [
						{"origin": [-3.375, -2.85273, 89.00767], "size": [6.75, 6.75, 8], "uv": [229, 105]}
					]
				},
				{
					"name": "1_tail7",
					"parent": "1_tail6",
					"pivot": [0, 0.52227, 98.00767],
					"cubes": [
						{"origin": [-2.375, -1.85273, 97.00767], "size": [4.75, 4.75, 6], "uv": [252, 155]},
						{"origin": [-2.375, -1.85273, 103.00767], "size": [4.75, 4.75, 4], "uv": [155, 77]}
					]
				},
				{
					"name": "1_tail8",
					"parent": "hip",
					"pivot": [0, 17.52227, 39.00767],
					"rotation": [17.5, 0, 0]
				},
				{
					"name": "1_tail9",
					"parent": "1_tail8",
					"pivot": [0, 17.52227, 45.25767]
				},
				{
					"name": "1_tail10",
					"parent": "1_tail9",
					"pivot": [0, 17.52227, 54.00767]
				},
				{
					"name": "1_tail11",
					"parent": "1_tail10",
					"pivot": [0, 17.52227, 64.50767]
				},
				{
					"name": "1_tail12",
					"parent": "1_tail11",
					"pivot": [0, 17.52227, 81.50767]
				},
				{
					"name": "1_tail13",
					"parent": "1_tail12",
					"pivot": [0, 17.52227, 91.50767]
				},
				{
					"name": "1_tail14",
					"parent": "1_tail13",
					"pivot": [0, 17.52227, 98.00767]
				},
				{
					"name": "L_tail",
					"parent": "hip",
					"pivot": [3.80755, 0.26844, 38.20262],
					"rotation": [17.89807, 11.91276, 3.81397],
					"cubes": [
						{"origin": [1.43255, -2.10656, 34.20262], "size": [4.75, 4.75, 12], "uv": [83, 215]}
					]
				},
				{
					"name": "L_tail2",
					"parent": "L_tail",
					"pivot": [3.80755, 0.26844, 44.45262],
					"cubes": [
						{"origin": [0.43255, -3.10656, 44.20262], "size": [6.75, 6.75, 10], "uv": [212, 181]}
					]
				},
				{
					"name": "L_tail3",
					"parent": "L_tail2",
					"pivot": [3.80755, 0.26844, 53.20262],
					"cubes": [
						{"origin": [-0.56745, -4.10656, 53.20262], "size": [8.75, 8.75, 13], "uv": [0, 140]}
					]
				},
				{
					"name": "L_tail4",
					"parent": "L_tail3",
					"pivot": [3.80755, 0.26844, 63.70262],
					"cubes": [
						{"origin": [-1.56745, -5.10656, 81.20262], "size": [10.75, 10.75, 7], "uv": [194, 105]},
						{"origin": [-1.56745, -5.10656, 63.20262], "size": [10.75, 10.75, 18], "uv": [39, 69]}
					]
				},
				{
					"name": "L_tail5",
					"parent": "L_tail4",
					"pivot": [3.80755, 0.26844, 80.70262],
					"cubes": [
						{"origin": [-0.56745, -4.10656, 78.20262], "size": [8.75, 8.75, 12], "uv": [165, 113]},
						{"origin": [-0.56745, -4.10656, 90.20262], "size": [8.75, 8.75, 5], "uv": [223, 237]}
					]
				},
				{
					"name": "L_tail6",
					"parent": "L_tail5",
					"pivot": [3.80755, 0.26844, 90.70262],
					"cubes": [
						{"origin": [0.43255, -3.10656, 88.20262], "size": [6.75, 6.75, 8], "uv": [229, 105]}
					]
				},
				{
					"name": "L_tail7",
					"parent": "L_tail6",
					"pivot": [3.80755, 0.26844, 97.20262],
					"cubes": [
						{"origin": [1.43255, -2.10656, 96.20262], "size": [4.75, 4.75, 6], "uv": [252, 155]},
						{"origin": [1.43255, -2.10656, 102.20262], "size": [4.75, 4.75, 4], "uv": [155, 77]}
					]
				},
				{
					"name": "R_tail8",
					"parent": "hip",
					"pivot": [-3.80755, 0.26844, 38.20262],
					"rotation": [17.89807, -11.91276, -3.81397],
					"cubes": [
						{"origin": [-6.18255, -2.10656, 34.20262], "size": [4.75, 4.75, 12], "uv": [83, 215]}
					]
				},
				{
					"name": "R_tail2",
					"parent": "R_tail8",
					"pivot": [-3.80755, 0.26844, 44.45262],
					"cubes": [
						{"origin": [-7.18255, -3.10656, 44.20262], "size": [6.75, 6.75, 10], "uv": [212, 181]}
					]
				},
				{
					"name": "R_tail3",
					"parent": "R_tail2",
					"pivot": [-3.80755, 0.26844, 53.20262],
					"cubes": [
						{"origin": [-8.18255, -4.10656, 53.20262], "size": [8.75, 8.75, 13], "uv": [0, 140]}
					]
				},
				{
					"name": "R_tail4",
					"parent": "R_tail3",
					"pivot": [-3.80755, 0.26844, 63.70262],
					"cubes": [
						{"origin": [-9.18255, -5.10656, 81.20262], "size": [10.75, 10.75, 7], "uv": [194, 105]},
						{"origin": [-9.18255, -5.10656, 63.20262], "size": [10.75, 10.75, 18], "uv": [39, 69]}
					]
				},
				{
					"name": "R_tail5",
					"parent": "R_tail4",
					"pivot": [-3.80755, 0.26844, 80.70262],
					"cubes": [
						{"origin": [-8.18255, -4.10656, 78.20262], "size": [8.75, 8.75, 12], "uv": [165, 113]},
						{"origin": [-8.18255, -4.10656, 90.20262], "size": [8.75, 8.75, 5], "uv": [223, 237]}
					]
				},
				{
					"name": "R_tail6",
					"parent": "R_tail5",
					"pivot": [-3.80755, 0.26844, 90.70262],
					"cubes": [
						{"origin": [-7.18255, -3.10656, 88.20262], "size": [6.75, 6.75, 8], "uv": [229, 105]}
					]
				},
				{
					"name": "R_tail7",
					"parent": "R_tail6",
					"pivot": [-3.80755, 0.26844, 97.20262],
					"cubes": [
						{"origin": [-6.18255, -2.10656, 96.20262], "size": [4.75, 4.75, 6], "uv": [252, 155]},
						{"origin": [-6.18255, -2.10656, 102.20262], "size": [4.75, 4.75, 4], "uv": [155, 77]}
					]
				},
				{
					"name": "2_tail",
					"parent": "hip",
					"pivot": [0, -8.3703, 42.15763],
					"rotation": [-12.5, 0, 0],
					"cubes": [
						{"origin": [-2.375, -10.7453, 38.15763], "size": [4.75, 4.75, 12], "uv": [83, 215]}
					]
				},
				{
					"name": "2_tail2",
					"parent": "2_tail",
					"pivot": [0, -8.3703, 48.40763],
					"cubes": [
						{"origin": [-3.375, -11.7453, 48.15763], "size": [6.75, 6.75, 10], "uv": [212, 181]}
					]
				},
				{
					"name": "2_tail3",
					"parent": "2_tail2",
					"pivot": [0, -8.3703, 57.15763],
					"cubes": [
						{"origin": [-4.375, -12.7453, 57.15763], "size": [8.75, 8.75, 13], "uv": [0, 140]}
					]
				},
				{
					"name": "2_tail4",
					"parent": "2_tail3",
					"pivot": [0, -8.3703, 67.65763],
					"cubes": [
						{"origin": [-5.375, -13.7453, 85.15763], "size": [10.75, 10.75, 7], "uv": [194, 105]},
						{"origin": [-5.375, -13.7453, 67.15763], "size": [10.75, 10.75, 18], "uv": [39, 69]}
					]
				},
				{
					"name": "2_tail5",
					"parent": "2_tail4",
					"pivot": [0, -8.3703, 84.65763],
					"cubes": [
						{"origin": [-4.375, -12.7453, 82.15763], "size": [8.75, 8.75, 12], "uv": [165, 113]},
						{"origin": [-4.375, -12.7453, 94.15763], "size": [8.75, 8.75, 5], "uv": [223, 237]}
					]
				},
				{
					"name": "2_tail6",
					"parent": "2_tail5",
					"pivot": [0, -8.3703, 94.65763],
					"cubes": [
						{"origin": [-3.375, -11.7453, 92.15763], "size": [6.75, 6.75, 8], "uv": [229, 105]}
					]
				},
				{
					"name": "2_tail7",
					"parent": "2_tail6",
					"pivot": [0, -8.3703, 101.15763],
					"cubes": [
						{"origin": [-2.375, -10.7453, 100.15763], "size": [4.75, 4.75, 6], "uv": [252, 155]},
						{"origin": [-2.375, -10.7453, 106.15763], "size": [4.75, 4.75, 4], "uv": [155, 77]}
					]
				},
				{
					"name": "C_tail",
					"parent": "hip",
					"pivot": [4.88148, -8.13607, 41.10109],
					"rotation": [-12.79362, 12.19908, -2.74715],
					"cubes": [
						{"origin": [2.50648, -10.51107, 37.10109], "size": [4.75, 4.75, 12], "uv": [83, 215]}
					]
				},
				{
					"name": "C_tail2",
					"parent": "C_tail",
					"pivot": [4.88148, -8.13607, 47.35109],
					"cubes": [
						{"origin": [1.50648, -11.51107, 47.10109], "size": [6.75, 6.75, 10], "uv": [212, 181]}
					]
				},
				{
					"name": "C_tail3",
					"parent": "C_tail2",
					"pivot": [4.88148, -8.13607, 56.10109],
					"cubes": [
						{"origin": [0.50648, -12.51107, 56.10109], "size": [8.75, 8.75, 13], "uv": [0, 140]}
					]
				},
				{
					"name": "C_tail4",
					"parent": "C_tail3",
					"pivot": [4.88148, -8.13607, 66.60109],
					"cubes": [
						{"origin": [-0.49352, -13.51107, 84.10109], "size": [10.75, 10.75, 7], "uv": [194, 105]},
						{"origin": [-0.49352, -13.51107, 66.10109], "size": [10.75, 10.75, 18], "uv": [39, 69]}
					]
				},
				{
					"name": "C_tail5",
					"parent": "C_tail4",
					"pivot": [4.88148, -8.13607, 83.60109],
					"cubes": [
						{"origin": [0.50648, -12.51107, 81.10109], "size": [8.75, 8.75, 12], "uv": [165, 113]},
						{"origin": [0.50648, -12.51107, 93.10109], "size": [8.75, 8.75, 5], "uv": [223, 237]}
					]
				},
				{
					"name": "C_tail6",
					"parent": "C_tail5",
					"pivot": [4.88148, -8.13607, 93.60109],
					"cubes": [
						{"origin": [1.50648, -11.51107, 91.10109], "size": [6.75, 6.75, 8], "uv": [229, 105]}
					]
				},
				{
					"name": "C_tail7",
					"parent": "C_tail6",
					"pivot": [4.88148, -8.13607, 100.10109],
					"cubes": [
						{"origin": [2.50648, -10.51107, 99.10109], "size": [4.75, 4.75, 6], "uv": [252, 155]},
						{"origin": [2.50648, -10.51107, 105.10109], "size": [4.75, 4.75, 4], "uv": [155, 77]}
					]
				},
				{
					"name": "D_tail",
					"parent": "hip",
					"pivot": [-4.88148, -8.13607, 41.10109],
					"rotation": [-12.79362, -12.19908, 2.74715],
					"cubes": [
						{"origin": [-7.25648, -10.51107, 37.10109], "size": [4.75, 4.75, 12], "uv": [83, 215]}
					]
				},
				{
					"name": "D_tail2",
					"parent": "D_tail",
					"pivot": [-4.88148, -8.13607, 47.35109],
					"cubes": [
						{"origin": [-8.25648, -11.51107, 47.10109], "size": [6.75, 6.75, 10], "uv": [212, 181]}
					]
				},
				{
					"name": "D_tail3",
					"parent": "D_tail2",
					"pivot": [-4.88148, -8.13607, 56.10109],
					"cubes": [
						{"origin": [-9.25648, -12.51107, 56.10109], "size": [8.75, 8.75, 13], "uv": [0, 140]}
					]
				},
				{
					"name": "D_tail4",
					"parent": "D_tail3",
					"pivot": [-4.88148, -8.13607, 66.60109],
					"cubes": [
						{"origin": [-10.25648, -13.51107, 84.10109], "size": [10.75, 10.75, 7], "uv": [194, 105]},
						{"origin": [-10.25648, -13.51107, 66.10109], "size": [10.75, 10.75, 18], "uv": [39, 69]}
					]
				},
				{
					"name": "D_tail5",
					"parent": "D_tail4",
					"pivot": [-4.88148, -8.13607, 83.60109],
					"cubes": [
						{"origin": [-9.25648, -12.51107, 81.10109], "size": [8.75, 8.75, 12], "uv": [165, 113]},
						{"origin": [-9.25648, -12.51107, 93.10109], "size": [8.75, 8.75, 5], "uv": [223, 237]}
					]
				},
				{
					"name": "D_tail6",
					"parent": "D_tail5",
					"pivot": [-4.88148, -8.13607, 93.60109],
					"cubes": [
						{"origin": [-8.25648, -11.51107, 91.10109], "size": [6.75, 6.75, 8], "uv": [229, 105]}
					]
				},
				{
					"name": "D_tail7",
					"parent": "D_tail6",
					"pivot": [-4.88148, -8.13607, 100.10109],
					"cubes": [
						{"origin": [-7.25648, -10.51107, 99.10109], "size": [4.75, 4.75, 6], "uv": [252, 155]},
						{"origin": [-7.25648, -10.51107, 105.10109], "size": [4.75, 4.75, 4], "uv": [155, 77]}
					]
				},
				{
					"name": "A_tail",
					"parent": "hip",
					"pivot": [4, -2.625, 40],
					"rotation": [0, 15, 0],
					"cubes": [
						{"origin": [1.625, -5, 36], "size": [4.75, 4.75, 12], "uv": [83, 215]}
					]
				},
				{
					"name": "A_tail2",
					"parent": "A_tail",
					"pivot": [4, -2.625, 46.25],
					"cubes": [
						{"origin": [0.625, -6, 46], "size": [6.75, 6.75, 10], "uv": [212, 181]}
					]
				},
				{
					"name": "A_tail3",
					"parent": "A_tail2",
					"pivot": [4, -2.625, 55],
					"cubes": [
						{"origin": [-0.375, -7, 55], "size": [8.75, 8.75, 13], "uv": [0, 140]}
					]
				},
				{
					"name": "A_tail4",
					"parent": "A_tail3",
					"pivot": [4, -2.625, 65.5],
					"cubes": [
						{"origin": [-1.375, -8, 83], "size": [10.75, 10.75, 7], "uv": [194, 105]},
						{"origin": [-1.375, -8, 65], "size": [10.75, 10.75, 18], "uv": [39, 69]}
					]
				},
				{
					"name": "A_tail5",
					"parent": "A_tail4",
					"pivot": [4, -2.625, 82.5],
					"cubes": [
						{"origin": [-0.375, -7, 80], "size": [8.75, 8.75, 12], "uv": [165, 113]},
						{"origin": [-0.375, -7, 92], "size": [8.75, 8.75, 5], "uv": [223, 237]}
					]
				},
				{
					"name": "A_tail6",
					"parent": "A_tail5",
					"pivot": [4, -2.625, 92.5],
					"cubes": [
						{"origin": [0.625, -6, 90], "size": [6.75, 6.75, 8], "uv": [229, 105]}
					]
				},
				{
					"name": "A_tail7",
					"parent": "A_tail6",
					"pivot": [4, -2.625, 99],
					"cubes": [
						{"origin": [1.625, -5, 98], "size": [4.75, 4.75, 6], "uv": [252, 155]},
						{"origin": [1.625, -5, 104], "size": [4.75, 4.75, 4], "uv": [155, 77]}
					]
				},
				{
					"name": "B_tail",
					"parent": "hip",
					"pivot": [-4, -2.625, 40],
					"rotation": [0, -15, 0],
					"cubes": [
						{"origin": [-6.375, -5, 36], "size": [4.75, 4.75, 12], "uv": [83, 215]}
					]
				},
				{
					"name": "B_tail2",
					"parent": "B_tail",
					"pivot": [-4, -2.625, 46.25],
					"cubes": [
						{"origin": [-7.375, -6, 46], "size": [6.75, 6.75, 10], "uv": [212, 181]}
					]
				},
				{
					"name": "B_tail3",
					"parent": "B_tail2",
					"pivot": [-4, -2.625, 55],
					"cubes": [
						{"origin": [-8.375, -7, 55], "size": [8.75, 8.75, 13], "uv": [0, 140]}
					]
				},
				{
					"name": "B_tail4",
					"parent": "B_tail3",
					"pivot": [-4, -2.625, 65.5],
					"cubes": [
						{"origin": [-9.375, -8, 83], "size": [10.75, 10.75, 7], "uv": [194, 105]},
						{"origin": [-9.375, -8, 65], "size": [10.75, 10.75, 18], "uv": [39, 69]}
					]
				},
				{
					"name": "B_tail5",
					"parent": "B_tail4",
					"pivot": [-4, -2.625, 82.5],
					"cubes": [
						{"origin": [-8.375, -7, 80], "size": [8.75, 8.75, 12], "uv": [165, 113]},
						{"origin": [-8.375, -7, 92], "size": [8.75, 8.75, 5], "uv": [223, 237]}
					]
				},
				{
					"name": "B_tail6",
					"parent": "B_tail5",
					"pivot": [-4, -2.625, 92.5],
					"cubes": [
						{"origin": [-7.375, -6, 90], "size": [6.75, 6.75, 8], "uv": [229, 105]}
					]
				},
				{
					"name": "B_tail7",
					"parent": "B_tail6",
					"pivot": [-4, -2.625, 99],
					"cubes": [
						{"origin": [-6.375, -5, 98], "size": [4.75, 4.75, 6], "uv": [252, 155]},
						{"origin": [-6.375, -5, 104], "size": [4.75, 4.75, 4], "uv": [155, 77]}
					]
				},
				{
					"name": "waist",
					"parent": "hip",
					"pivot": [0, -4, 31],
					"cubes": [
						{"origin": [-5.5, -10, 19], "size": [11, 12, 14], "uv": [0, 87]}
					]
				},
				{
					"name": "chest",
					"parent": "waist",
					"pivot": [0.16667, -3.0499, 21.64351],
					"cubes": [
						{"origin": [-8, -16, 7], "size": [16, 19.7, 7], "inflate": 0.01, "pivot": [0, -4.65, 15], "rotation": [-12.5, 0, 0], "uv": [49, 116]},
						{"origin": [-12, -20, 7], "size": [24, 25.7, 0], "pivot": [-1, -4.65, 15], "rotation": [-12.5, 0, 0], "uv": [0, 114]},
						{"origin": [-7, -13, 9], "size": [14, 16.7, 12], "pivot": [0, -4.65, 15], "rotation": [-4, 0, 0], "uv": [84, 87]}
					]
				},
				{
					"name": "LeftArm",
					"parent": "chest",
					"pivot": [7, -9.03192, 12.79541],
					"cubes": [
						{"origin": [4, -17.65, 9], "size": [6, 13, 8], "pivot": [7, -12.15, 13.5], "rotation": [12.5, 0, 0], "uv": [0, 203]}
					]
				},
				{
					"name": "LeftArm2",
					"parent": "LeftArm",
					"pivot": [7, -17.4, 13.5],
					"cubes": [
						{"origin": [5, -29.65, 11], "size": [4, 14, 5], "uv": [46, 242]}
					]
				},
				{
					"name": "LeftArm3",
					"parent": "LeftArm2",
					"pivot": [6.8125, -29.93125, 13.8125],
					"cubes": [
						{"origin": [6.25, -31.15, 7.25], "size": [1.25, 2.25, 2.5], "uv": [46, 69]},
						{"origin": [3.75, -31.4, 7.5], "size": [1.25, 2.25, 2.5], "uv": [39, 69]},
						{"origin": [8.5, -31.4, 7.5], "size": [1.25, 2.25, 2.5], "uv": [64, 0]},
						{"origin": [4.25, -32.65, 8], "size": [5.25, 3, 8.5], "uv": [19, 242]}
					]
				},
				{
					"name": "RightArm",
					"parent": "chest",
					"pivot": [-7, -9.03192, 12.79541],
					"cubes": [
						{"origin": [-10, -17.65, 9], "size": [6, 13, 8], "pivot": [-7, -12.15, 13.5], "rotation": [12.5, 0, 0], "uv": [105, 198]}
					]
				},
				{
					"name": "RightArm2",
					"parent": "RightArm",
					"pivot": [-7, -17.4, 13.5],
					"cubes": [
						{"origin": [-9, -29.65, 11], "size": [4, 14, 5], "uv": [0, 241]}
					]
				},
				{
					"name": "RightArm3",
					"parent": "RightArm2",
					"pivot": [-6.8125, -29.93125, 13.8125],
					"cubes": [
						{"origin": [-7.5, -31.15, 7.25], "size": [1.25, 2.25, 2.5], "uv": [10, 58]},
						{"origin": [-5, -31.4, 7.5], "size": [1.25, 2.25, 2.5], "uv": [48, 11]},
						{"origin": [-9.75, -31.4, 7.5], "size": [1.25, 2.25, 2.5], "uv": [46, 40]},
						{"origin": [-9.5, -32.65, 8], "size": [5.25, 3, 8.5], "uv": [238, 120]}
					]
				},
				{
					"name": "neck",
					"parent": "chest",
					"pivot": [0, -1.43161, 7.72623],
					"cubes": [
						{"origin": [-5.5, -12, 5], "size": [11, 14.3, 7], "pivot": [1.5, -5, 14], "rotation": [-15, 0, 0], "uv": [185, 134]}
					]
				},
				{
					"name": "neck2",
					"parent": "neck",
					"pivot": [0, -1.59236, 6.29133],
					"cubes": [
						{"origin": [-4.5, -5.37046, 0.93906], "size": [9, 7.9, 11.1], "pivot": [0, -2.37046, 6.13906], "rotation": [60, 0, 0], "uv": [180, 17]}
					]
				},
				{
					"name": "neck3",
					"parent": "neck2",
					"pivot": [0, 1.11148, 2.81216],
					"cubes": [
						{"origin": [-3.5, -3, -2.25], "size": [7, 8.5, 7], "pivot": [0, 1, 2.75], "rotation": [-37.5, 0, 0], "uv": [0, 225]}
					]
				},
				{
					"name": "Head",
					"parent": "neck3",
					"pivot": [0, 4, 0],
					"cubes": [
						{"origin": [-4, 1, -6], "size": [8, 7, 8], "uv": [117, 0]},
						{"origin": [5.33336, -3.0658, -2.58663], "size": [0, 10.1, 10.5], "pivot": [1.33336, 2.5342, 1.66337], "rotation": [-43.91427, 23.50373, -13.454], "uv": [148, 232]},
						{"origin": [-5.33336, -3.0658, -2.58663], "size": [0, 10.1, 10.5], "pivot": [-1.33336, 2.5342, 1.66337], "rotation": [-43.91427, -23.50373, 13.454], "uv": [127, 230]},
						{"origin": [3.4, 5, -1.5], "size": [2, 8, 5], "pivot": [5.9, 11, -0.5], "rotation": [-36.19714, 10.54794, 14.04397], "uv": [98, 255]},
						{"origin": [5.15, 5, -3.5], "size": [0, 11, 8], "pivot": [5.9, 11, -0.5], "rotation": [-36.19714, 10.54794, 14.04397], "uv": [65, 242]},
						{"origin": [-5.15, 5, -3.5], "size": [0, 11, 8], "pivot": [-5.9, 11, -0.5], "rotation": [-36.19714, -10.54794, -14.04397], "uv": [108, 240]},
						{"origin": [-5.4, 5, -1.5], "size": [2, 8, 5], "pivot": [-5.9, 11, -0.5], "rotation": [-36.19714, -10.54794, -14.04397], "uv": [0, 58]},
						{"origin": [-2.5, 1, -14], "size": [5, 4, 8], "uv": [190, 36]},
						{"origin": [1.85, -1, -13.6], "size": [0, 2, 7.6], "uv": [52, 210]},
						{"origin": [-1.85, -1, -13.6], "size": [3.7, 2, 0], "uv": [11, 29]},
						{"origin": [-1.85, -1, -13.6], "size": [0, 2, 7.6], "uv": [206, 123]},
						{"origin": [-1, 3, -14.5], "size": [2, 2.5, 2.25], "uv": [39, 11]}
					]
				},
				{
					"name": "bone2",
					"parent": "Head",
					"pivot": [0, 0.875, -2.9375],
					"cubes": [
						{"origin": [-4, -1.5, -6], "size": [8, 2.5, 8], "uv": [39, 0]},
						{"origin": [-2, -1, -13.75], "size": [4, 2, 7.75], "uv": [143, 149]},
						{"origin": [-1.75, 1, -13.5], "size": [0, 2, 7.5], "uv": [134, 198]},
						{"origin": [-1.75, 1, -13.5], "size": [3.5, 2, 0], "uv": [11, 0]},
						{"origin": [1.75, 1, -13.5], "size": [0, 2, 7.5], "uv": [196, 181]}
					]
				},
				{
					"name": "fx1",
					"pivot": [0, 0, 0],
					"locators": {
						"fx1": {
							"offset": [0, 0, 0],
							"rotation": [0, 0, -180]
						}
					}
				}
			]
		}
	]
}