{
	"format_version": "1.12.0",
	"minecraft:geometry": [
		{
			"description": {
				"identifier": "geometry.bossbar",
				"texture_width": 16,
				"texture_height": 16,
				"visible_bounds_width": 1,
				"visible_bounds_height": 1,
				"visible_bounds_offset": [0, 0, 0]
			},
			"bones": [
				{
					"name": "bossbar_root",
					"pivot": [0, 0, 0]
				},
				{
					"name": "bossbar",
					"parent": "bossbar_root",
					"pivot": [0, 0, 0],
					"locators": {
						"locator_bossbar": [0, 0, 0]
					}
				},
				{
					"name": "bossbar2",
					"parent": "bossbar_root",
					"pivot": [0, 0, 0],
					"locators": {
						"locator_bossbar2": [0, 0, 0]
					}
				}
			]
		}
	]
}